taifun/__init__.py
taifun/openai_api.py
taifun/runner.py
taifun/taifun.py
taifun-0.2.0.dist-info/METADATA
taifun-0.2.0.dist-info/WHEEL
taifun-0.2.0.dist-info/RECORD
