Metadata-Version: 2.1
Name: taifun
Version: 0.2.0
Summary: Function mapper for Open AI Chat
Author: Max Fröhlich
Author-email: maxbruchmann@gmail.com
Requires-Python: >=3.11,<4.0
Classifier: Programming Language :: Python :: 3
Classifier: Programming Language :: Python :: 3.11
Requires-Dist: docstring-parser (>=0.15,<0.16)
Requires-Dist: httpx (>=0.24.1,<0.25.0)
Requires-Dist: openai (>=0.27.8,<0.28.0)
Requires-Dist: pydantic (>=2.0,<3.0)
Requires-Dist: rich (>=13.4.2,<14.0.0)
Requires-Dist: typer (>=0.9.0,<0.10.0)
